popelines/__init__.py
popelines/copy_table.py
popelines/main.py
popelines-0.1.22.dist-info/LICENSE
popelines-0.1.22.dist-info/METADATA
popelines-0.1.22.dist-info/WHEEL
popelines-0.1.22.dist-info/top_level.txt
popelines-0.1.22.dist-info/RECORD
