Metadata-Version: 2.1
Name: popelines
Version: 0.1.22
Summary: An ETL library for Google BigQuery
Home-page: https://github.com/InfusionsoftAnalytics/popelines
Author: Daniel Francis
Author-email: daniel.francis@infusionsoft.com
License: MIT
Platform: UNKNOWN
Classifier: Programming Language :: Python :: 3
Classifier: License :: OSI Approved :: MIT License
Classifier: Operating System :: OS Independent
Requires-Dist: google-cloud-storage
Requires-Dist: google-cloud-bigquery
Requires-Dist: bigquery-schema-generator
